moduledocs/__init__.py
moduledocs/cli.py
moduledocs/parse.py
moduledocs/parsed_objects.py
moduledocs/style_base.py
moduledocs/style_markdown.py
moduledocs-1.0.1.dist-info/LICENSE
moduledocs-1.0.1.dist-info/METADATA
moduledocs-1.0.1.dist-info/WHEEL
moduledocs-1.0.1.dist-info/entry_points.txt
moduledocs-1.0.1.dist-info/top_level.txt
moduledocs-1.0.1.dist-info/RECORD
